NewAlpha/__init__.py
NewAlpha/newalpha.py
NewAlpha-1.1.1.dist-info/LICENSE
NewAlpha-1.1.1.dist-info/METADATA
NewAlpha-1.1.1.dist-info/WHEEL
NewAlpha-1.1.1.dist-info/top_level.txt
NewAlpha-1.1.1.dist-info/RECORD
